djrest/__init__.py
djrest/__version__.py
djrest/response.py
djrest/views.py
djrest2-0.2.0.dist-info/licenses/LICENSE
djrest2-0.2.0.dist-info/METADATA
djrest2-0.2.0.dist-info/WHEEL
djrest2-0.2.0.dist-info/top_level.txt
djrest2-0.2.0.dist-info/RECORD
