Metadata-Version: 2.4
Name: djrest2
Version: 0.2.0
Summary: A small and simple REST library for Django based on class-based views
Author-email: Emma Delescolle <emma@levit.be>
License: MIT
Project-URL: Homepage, https://gitlab.levitnet.be/levit/djrest
Project-URL: Repository, https://gitlab.levitnet.be/levit/djrest.git
Project-URL: Documentation, https://emma.has-a.blog/articles/why-do-we-need-an-external-app-for-rest.html
Keywords: django,rest,api,class-based-views
Classifier: Development Status :: 3 - Alpha
Classifier: Framework :: Django
Classifier: Framework :: Django :: 4.2
Classifier: Framework :: Django :: 5.0
Classifier: Framework :: Django :: 5.1
Classifier: Intended Audience :: Developers
Classifier: License :: OSI Approved :: MIT License
Classifier: Operating System :: OS Independent
Classifier: Programming Language :: Python :: 3
Classifier: Programming Language :: Python :: 3.11
Classifier: Programming Language :: Python :: 3.12
Classifier: Programming Language :: Python :: 3.13
Classifier: Topic :: Internet :: WWW/HTTP
Classifier: Topic :: Software Development :: Libraries :: Python Modules
Requires-Python: >=3.11
License-File: LICENSE
Requires-Dist: Django>=4.2
Provides-Extra: dev
Requires-Dist: pytest; extra == "dev"
Requires-Dist: pytest-django; extra == "dev"
Requires-Dist: pytest-cov; extra == "dev"
Requires-Dist: ruff; extra == "dev"
Requires-Dist: nox; extra == "dev"
Requires-Dist: factory-boy; extra == "dev"
Requires-Dist: django-classy-doc; extra == "dev"
Requires-Dist: uv; extra == "dev"
Dynamic: license-file
